FIR/fir.v
module firfilter #(
    parameter DATA_SIZE = 9,
    parameter N_TAPS = 3
)
(
    input clk,
    input signed [DATA_SIZE-1:0] data,
    input data_ready,

    // output reg [DATA_SIZE-1:0] res = 0,
    output reg [DATA_SIZE-1:0] summ = 0
);


reg signed [DATA_SIZE-1:0] buff[N_TAPS-1:0];
reg signed [7:0] i = 0;
reg signed [7:0] j = 0;
reg signed [DATA_SIZE-1:0] coef[N_TAPS-1:0];

wire signed [15:0] mult, m0, m1;
reg [7:0] cnt_mult = 0;

assign mult = m0*m1;
assign m0 = buff[cnt_mult];
assign m1 = coef[cnt_mult];

initial
begin
    buff[0] = 0;
    buff[1] = 0;
    buff[2] = 0;
    for(j=0; j<N_TAPS; j=j+1)
    begin
        coef[j] <= (j+i);
    end
end

// always @(posedge clk) 
// begin
//     if (data_ready) 
//     begin
//     buff[0] = buff[1];
//     buff[1] = buff[2];
//     buff[2] = data;
//     end
//     res = 0;
//     for (i=0; i<N_TAPS; i=i+1)
//     begin
//         res = res + coef[i]*buff[i];
//     end    
// end


always @(posedge clk)
begin
    if (data_ready) 
    begin
        buff[0] = buff[1];
        buff[1] = buff[2];
        buff[2] = data;
    end
    summ <= cnt_mult == 0 ? mult : summ + mult;
    cnt_mult <= data_ready == 1 ? 0 : cnt_mult + 1;
end


endmodule

FIR/test.v
module tb;
    reg clk = 0;
    parameter DATA_SIZE = 9;
    parameter N_TAPS = 3;
    reg signed [DATA_SIZE - 1:0] data = 'h753;

    reg data_ready = 0;

    reg signed [7:0] i = 0;
    reg signed [DATA_SIZE-1:0] buff[11:0];

    initial
    begin
        buff[0] <= 16'h10;
        buff[1] <= 16'h15;
        buff[2] <= 16'h20;
        buff[3] <= 16'h25;
        buff[4] <= 16'h30; 
        buff[5] <= 16'h35;
        buff[6] <= 16'h40;
        buff[7] <= 16'h45;
        buff[8] <= 16'h50;
        buff[9] <= 16'h55;
        buff[10] <= 16'h60;
        buff[11] <= 16'h65;
    end

    initial 
    begin
        forever #20 clk = ~clk; 
    end

    initial
    begin
        for(i=0; i<12; i=i+1)
        begin
            #360;
            data <= buff[i];
            #10;
            data_ready = 1;
            #30;
            data_ready = 0;

        end
    end

    initial
    begin
        #5000 $finish;
    end

    initial
    begin
        $dumpfile("dump.vcd");
        $dumpvars(0, tb);
    end

    firfilter #( .DATA_SIZE(DATA_SIZE),
    .N_TAPS(N_TAPS) )
    fir0 (
        .clk(clk),
        .data(data),
        .data_ready(data_ready)
    );

endmodule

FIR/dump.vcd
$date
	Thu May 04 17:00:48 2023
$end
$version
	Icarus Verilog
$end
$timescale
	1s
$end
$scope module tb $end
$var reg 1 ! clk $end
$var reg 9 " data [8:0] $end
$var reg 1 # data_ready $end
$var reg 8 $ i [7:0] $end
$scope module fir0 $end
$var wire 1 % clk $end
$var wire 9 & data [8:0] $end
$var wire 1 ' data_ready $end
$var wire 16 ( m0 [15:0] $end
$var wire 16 ) m1 [15:0] $end
$var wire 16 * mult [15:0] $end
$var reg 8 + cnt_mult [7:0] $end
$var reg 8 , i [7:0] $end
$var reg 8 - j [7:0] $end
$var reg 9 . summ [8:0] $end
$upscope $end
$upscope $end
$enddefinitions $end
#0
$dumpvars
b0 .
b11 -
b0 ,
b0 +
b0 *
b0 )
b0 (
0'
b101010011 &
0%
b0 $
0#
b101010011 "
0!
$end
#20
b1 +
b1 )
1!
1%
#40
0!
0%
#60
b10 +
b10 )
1!
1%
#80
0!
0%
#100
b11 +
bx (
bx *
bx )
1!
1%
#120
0!
0%
#140
b100 +
bx .
1!
1%
#160
0!
0%
#180
b101 +
1!
1%
#200
0!
0%
#220
b110 +
1!
1%
#240
0!
0%
#260
b111 +
1!
1%
#280
0!
0%
#300
b1000 +
1!
1%
#320
0!
0%
#340
b1001 +
1!
1%
#360
b10000 "
b10000 &
0!
0%
#370
1#
1'
#380
b0 +
b0 *
b0 (
b0 )
1!
1%
#400
0!
0%
b1 $
0#
0'
#420
b1 +
b1 )
b0 .
1!
1%
#440
0!
0%
#460
b10 +
b100000 *
b10000 (
b10 )
1!
1%
#480
0!
0%
#500
b11 +
bx (
bx *
bx )
b100000 .
1!
1%
#520
0!
0%
#540
b100 +
bx .
1!
1%
#560
0!
0%
#580
b101 +
1!
1%
#600
0!
0%
#620
b110 +
1!
1%
#640
0!
0%
#660
b111 +
1!
1%
#680
0!
0%
#700
b1000 +
1!
1%
#720
0!
0%
#740
b1001 +
1!
1%
#760
b10101 "
b10101 &
0!
0%
#770
1#
1'
#780
b0 +
b0 *
b0 (
b0 )
1!
1%
#800
0!
0%
b10 $
0#
0'
#820
b1 +
b10000 *
b10000 (
b1 )
b0 .
1!
1%
#840
0!
0%
#860
b10 +
b10101 (
b101010 *
b10 )
b10000 .
1!
1%
#880
0!
0%
#900
b11 +
bx (
bx *
bx )
b111010 .
1!
1%
#920
0!
0%
#940
b100 +
bx .
1!
1%
#960
0!
0%
#980
b101 +
1!
1%
#1000
0!
0%
#1020
b110 +
1!
1%
#1040
0!
0%
#1060
b111 +
1!
1%
#1080
0!
0%
#1100
b1000 +
1!
1%
#1120
0!
0%
#1140
b1001 +
1!
1%
#1160
b100000 "
b100000 &
0!
0%
#1170
1#
1'
#1180
b0 +
b0 *
b10000 (
b0 )
1!
1%
#1200
0!
0%
b11 $
0#
0'
#1220
b1 +
b10101 (
b10101 *
b1 )
b0 .
1!
1%
#1240
0!
0%
#1260
b10 +
b100000 (
b1000000 *
b10 )
b10101 .
1!
1%
#1280
0!
0%
#1300
b11 +
bx (
bx *
bx )
b1010101 .
1!
1%
#1320
0!
0%
#1340
b100 +
bx .
1!
1%
#1360
0!
0%
#1380
b101 +
1!
1%
#1400
0!
0%
#1420
b110 +
1!
1%
#1440
0!
0%
#1460
b111 +
1!
1%
#1480
0!
0%
#1500
b1000 +
1!
1%
#1520
0!
0%
#1540
b1001 +
1!
1%
#1560
b100101 "
b100101 &
0!
0%
#1570
1#
1'
#1580
b0 +
b0 *
b10101 (
b0 )
1!
1%
#1600
0!
0%
b100 $
0#
0'
#1620
b1 +
b100000 (
b100000 *
b1 )
b0 .
1!
1%
#1640
0!
0%
#1660
b10 +
b100101 (
b1001010 *
b10 )
b100000 .
1!
1%
#1680
0!
0%
#1700
b11 +
bx (
bx *
bx )
b1101010 .
1!
1%
#1720
0!
0%
#1740
b100 +
bx .
1!
1%
#1760
0!
0%
#1780
b101 +
1!
1%
#1800
0!
0%
#1820
b110 +
1!
1%
#1840
0!
0%
#1860
b111 +
1!
1%
#1880
0!
0%
#1900
b1000 +
1!
1%
#1920
0!
0%
#1940
b1001 +
1!
1%
#1960
b110000 "
b110000 &
0!
0%
#1970
1#
1'
#1980
b0 +
b0 *
b100000 (
b0 )
1!
1%
#2000
0!
0%
b101 $
0#
0'
#2020
b1 +
b100101 (
b100101 *
b1 )
b0 .
1!
1%
#2040
0!
0%
#2060
b10 +
b110000 (
b1100000 *
b10 )
b100101 .
1!
1%
#2080
0!
0%
#2100
b11 +
bx (
bx *
bx )
b10000101 .
1!
1%
#2120
0!
0%
#2140
b100 +
bx .
1!
1%
#2160
0!
0%
#2180
b101 +
1!
1%
#2200
0!
0%
#2220
b110 +
1!
1%
#2240
0!
0%
#2260
b111 +
1!
1%
#2280
0!
0%
#2300
b1000 +
1!
1%
#2320
0!
0%
#2340
b1001 +
1!
1%
#2360
b110101 "
b110101 &
0!
0%
#2370
1#
1'
#2380
b0 +
b0 *
b100101 (
b0 )
1!
1%
#2400
0!
0%
b110 $
0#
0'
#2420
b1 +
b110000 (
b110000 *
b1 )
b0 .
1!
1%
#2440
0!
0%
#2460
b10 +
b110101 (
b1101010 *
b10 )
b110000 .
1!
1%
#2480
0!
0%
#2500
b11 +
bx (
bx *
bx )
b10011010 .
1!
1%
#2520
0!
0%
#2540
b100 +
bx .
1!
1%
#2560
0!
0%
#2580
b101 +
1!
1%
#2600
0!
0%
#2620
b110 +
1!
1%
#2640
0!
0%
#2660
b111 +
1!
1%
#2680
0!
0%
#2700
b1000 +
1!
1%
#2720
0!
0%
#2740
b1001 +
1!
1%
#2760
b1000000 "
b1000000 &
0!
0%
#2770
1#
1'
#2780
b0 +
b0 *
b110000 (
b0 )
1!
1%
#2800
0!
0%
b111 $
0#
0'
#2820
b1 +
b110101 (
b110101 *
b1 )
b0 .
1!
1%
#2840
0!
0%
#2860
b10 +
b1000000 (
b10000000 *
b10 )
b110101 .
1!
1%
#2880
0!
0%
#2900
b11 +
bx (
bx *
bx )
b10110101 .
1!
1%
#2920
0!
0%
#2940
b100 +
bx .
1!
1%
#2960
0!
0%
#2980
b101 +
1!
1%
#3000
0!
0%
#3020
b110 +
1!
1%
#3040
0!
0%
#3060
b111 +
1!
1%
#3080
0!
0%
#3100
b1000 +
1!
1%
#3120
0!
0%
#3140
b1001 +
1!
1%
#3160
b1000101 "
b1000101 &
0!
0%
#3170
1#
1'
#3180
b0 +
b0 *
b110101 (
b0 )
1!
1%
#3200
0!
0%
b1000 $
0#
0'
#3220
b1 +
b1000000 (
b1000000 *
b1 )
b0 .
1!
1%
#3240
0!
0%
#3260
b10 +
b1000101 (
b10001010 *
b10 )
b1000000 .
1!
1%
#3280
0!
0%
#3300
b11 +
bx (
bx *
bx )
b11001010 .
1!
1%
#3320
0!
0%
#3340
b100 +
bx .
1!
1%
#3360
0!
0%
#3380
b101 +
1!
1%
#3400
0!
0%
#3420
b110 +
1!
1%
#3440
0!
0%
#3460
b111 +
1!
1%
#3480
0!
0%
#3500
b1000 +
1!
1%
#3520
0!
0%
#3540
b1001 +
1!
1%
#3560
b1010000 "
b1010000 &
0!
0%
#3570
1#
1'
#3580
b0 +
b0 *
b1000000 (
b0 )
1!
1%
#3600
0!
0%
b1001 $
0#
0'
#3620
b1 +
b1000101 (
b1000101 *
b1 )
b0 .
1!
1%
#3640
0!
0%
#3660
b10 +
b1010000 (
b10100000 *
b10 )
b1000101 .
1!
1%
#3680
0!
0%
#3700
b11 +
bx (
bx *
bx )
b11100101 .
1!
1%
#3720
0!
0%
#3740
b100 +
bx .
1!
1%
#3760
0!
0%
#3780
b101 +
1!
1%
#3800
0!
0%
#3820
b110 +
1!
1%
#3840
0!
0%
#3860
b111 +
1!
1%
#3880
0!
0%
#3900
b1000 +
1!
1%
#3920
0!
0%
#3940
b1001 +
1!
1%
#3960
b1010101 "
b1010101 &
0!
0%
#3970
1#
1'
#3980
b0 +
b0 *
b1000101 (
b0 )
1!
1%
#4000
0!
0%
b1010 $
0#
0'
#4020
b1 +
b1010000 (
b1010000 *
b1 )
b0 .
1!
1%
#4040
0!
0%
#4060
b10 +
b1010101 (
b10101010 *
b10 )
b1010000 .
1!
1%
#4080
0!
0%
#4100
b11 +
bx (
bx *
bx )
b11111010 .
1!
1%
#4120
0!
0%
#4140
b100 +
bx .
1!
1%
#4160
0!
0%
#4180
b101 +
1!
1%
#4200
0!
0%
#4220
b110 +
1!
1%
#4240
0!
0%
#4260
b111 +
1!
1%
#4280
0!
0%
#4300
b1000 +
1!
1%
#4320
0!
0%
#4340
b1001 +
1!
1%
#4360
b1100000 "
b1100000 &
0!
0%
#4370
1#
1'
#4380
b0 +
b0 *
b1010000 (
b0 )
1!
1%
#4400
0!
0%
b1011 $
0#
0'
#4420
b1 +
b1010101 (
b1010101 *
b1 )
b0 .
1!
1%
#4440
0!
0%
#4460
b10 +
b1100000 (
b11000000 *
b10 )
b1010101 .
1!
1%
#4480
0!
0%
#4500
b11 +
bx (
bx *
bx )
b100010101 .
1!
1%
#4520
0!
0%
#4540
b100 +
bx .
1!
1%
#4560
0!
0%
#4580
b101 +
1!
1%
#4600
0!
0%
#4620
b110 +
1!
1%
#4640
0!
0%
#4660
b111 +
1!
1%
#4680
0!
0%
#4700
b1000 +
1!
1%
#4720
0!
0%
#4740
b1001 +
1!
1%
#4760
b1100101 "
b1100101 &
0!
0%
#4770
1#
1'
#4780
b0 +
b0 *
b1010101 (
b0 )
1!
1%
#4800
0!
0%
b1100 $
0#
0'
#4820
b1 +
b1100000 (
b1100000 *
b1 )
b0 .
1!
1%
#4840
0!
0%
#4860
b10 +
b1100101 (
b11001010 *
b10 )
b1100000 .
1!
1%
#4880
0!
0%
#4900
b11 +
bx (
bx *
bx )
b100101010 .
1!
1%
#4920
0!
0%
#4940
b100 +
bx .
1!
1%
#4960
0!
0%
#4980
b101 +
1!
1%
